{"_id":{"$oid":"56e687ca0f0000380018ef59"},"item_id":1,"author_id":1,"author_name":"普京","posted":"2016-03-12T7:20:01.000Z","text":"放个核弹","timeline":1234560,"like":16}
{"_id":{"$oid":"56e687eb0f0000380018ef5a"},"item_id":1,"author_id":2,"author_name":"奥巴马","posted":"2016-03-12T8:31:01.000Z","text":"跟，两个氢弹","timeline":1234567,"like":1}
{"_id":{"$oid":"56e8f3b50f0000f60118ef5b"},"item_id":5716,"author_id":1,"author_name":"习近平","posted":"2016-03-16T05:45:50.247Z","text":"放个核弹","timeline":9,"like":0}
{"_id":{"$oid":"56e90c020f0000080218ef5c"},"timeline":10,"author_name":"习近平","text":"好课程","author_id":1,"like":0,"posted":"2016-03-16T07:32:17.777Z","item_id":1733}
{"_id":{"$oid":"56e917470f0000010218ef5d"},"timeline":0,"author_name":"习近平","text":"新的","author_id":1,"like":0,"posted":"2016-03-16T08:20:22.849Z","item_id":1}
{"_id":{"$oid":"56e9177a0f0000120218ef5e"},"timeline":17,"author_name":"习近平","text":"好","author_id":1,"like":0,"posted":"2016-03-16T08:21:14.619Z","item_id":1}
{"_id":{"$oid":"56e91af10f00001d0218ef5f"},"timeline":0,"author_name":"习近平","text":"有意思","author_id":1,"like":0,"posted":"2016-03-16T08:36:01.675Z","item_id":1}
{"_id":{"$oid":"56e91c190f00001c0218ef60"},"timeline":7,"author_name":"习近平","text":"好评！","author_id":1,"like":0,"posted":"2016-03-16T08:40:56.860Z","item_id":1}
{"_id":{"$oid":"56e91fc30f00002d0218ef61"},"timeline":0,"author_name":"习近平","text":"太好了","author_id":1,"like":0,"posted":"2016-03-16T08:56:35.109Z","item_id":1}
{"_id":{"$oid":"56e920d20f0000310218ef62"},"timeline":0,"author_name":"习近平","text":"好看","author_id":1,"like":0,"posted":"2016-03-16T09:01:06.029Z","item_id":1}
{"_id":{"$oid":"56ee5c44100000bc0110e8b8"},"timeline":6,"author_name":"习近平","text":"好的","author_id":1,"like":0,"posted":"2016-03-20T08:16:04.139Z","item_id":1}
{"_id":{"$oid":"56f00cdc1b0000b20044c863"},"timeline":6,"author_name":"杨典","text":"有意思","author_id":1,"like":0,"posted":"2016-03-21T15:01:48.550Z","item_id":1}
{"_id":{"$oid":"56f00e5d1b0000c70044c867"},"timeline":22,"author_name":"杨典","text":"好评","author_id":1,"like":0,"posted":"2016-03-21T15:08:12.017Z","item_id":1}
{"_id":{"$oid":"56f00ec31b0000d00044c869"},"timeline":5,"author_name":"杨典","text":"好评","author_id":1,"like":0,"posted":"2016-03-21T15:09:54.862Z","item_id":1}
{"_id":{"$oid":"56f00f5a1b0000d60044c86c"},"timeline":4,"author_name":"杨典","text":"好喜欢","author_id":1,"like":0,"posted":"2016-03-21T15:12:26.360Z","item_id":1}
{"_id":{"$oid":"56f017241800003c00f38f3f"},"timeline":10,"author_name":"习近平","text":"你好","author_id":1,"like":0,"posted":"2016-03-21T15:45:40.643Z","item_id":1}
{"_id":{"$oid":"56f0e1b1180000e100f38f46"},"timeline":9,"author_name":"刘杨","text":"你好","author_id":1,"like":0,"posted":"2016-03-22T06:09:53.163Z","item_id":1}
{"_id":{"$oid":"56f0e1e5180000e900f38f48"},"timeline":4,"author_name":"刘杨","text":"你好","author_id":1,"like":0,"posted":"2016-03-22T06:10:45.720Z","item_id":1}
{"_id":{"$oid":"56f20bb11800000502f38f79"},"timeline":9,"author_name":"杨典","text":"教育很重要","author_id":3,"like":0,"posted":"2016-03-23T03:21:21.057Z","item_id":1540}
{"_id":{"$oid":"56f214201800001c02f38f7f"},"item_id":7060,"author_id":6,"author_name":"匿名用户","posted":"2016-03-23T03:57:20.313Z","text":"fun","timeline":0,"like":0}
{"_id":{"$oid":"56f2172c1800001d02f38f81"},"timeline":7,"author_name":"杨典","text":"好","author_id":3,"like":0,"posted":"2016-03-23T04:10:20.377Z","item_id":2988}
{"_id":{"$oid":"56f258b0180000400178f73c"},"item_id":2334,"author_id":6,"author_name":"匿名用户","posted":"2016-03-23T08:49:52.353Z","text":"","timeline":2,"like":0}
{"_id":{"$oid":"56f49c3d0d00003f00eaa00e"},"item_id":6745,"author_id":9,"author_name":"匿名用户","posted":"2016-03-25T02:02:34.529Z","text":"","timeline":38,"like":0}
{"_id":{"$oid":"56f4e1281800003100a1ca91"},"timeline":15,"author_name":"刘杨","text":"神奇","author_id":5,"like":0,"posted":"2016-03-25T06:56:40.936Z","item_id":8253}
{"_id":{"$oid":"56f511b21800009600a1ca98"},"timeline":0,"author_name":"杨典","text":"good","author_id":3,"like":0,"posted":"2016-03-25T10:23:44.952Z","item_id":5385}
{"_id":{"$oid":"56f513451800009f00a1ca9b"},"timeline":6,"author_name":"杨典","text":"good","author_id":3,"like":0,"posted":"2016-03-25T10:30:08.108Z","item_id":676}
{"_id":{"$oid":"56f5138f180000a100a1ca9e"},"timeline":9,"author_name":"杨典","text":"good","author_id":3,"like":0,"posted":"2016-03-25T10:31:01.925Z","item_id":676}
{"_id":{"$oid":"56f53d83180000b700a1caa1"},"timeline":0,"author_name":"刘杨","text":"高难度","author_id":5,"like":0,"posted":"2016-03-25T13:30:43.069Z","item_id":223}
{"_id":{"$oid":"56f53eee180000b700a1caa6"},"timeline":22,"author_name":"刘杨","text":"解放军万岁","author_id":5,"like":0,"posted":"2016-03-25T13:36:46.154Z","item_id":4756}
{"_id":{"$oid":"56f9e3442a00003200d6187e"},"timeline":21,"author_name":"杨典","text":"好吃","author_id":3,"like":0,"posted":"2016-03-29T02:06:31.863Z","item_id":823}
{"_id":{"$oid":"56f9e3ad2a00004100d61880"},"timeline":8,"author_name":"杨典","text":"好吃","author_id":3,"like":0,"posted":"2016-03-29T02:08:10.282Z","item_id":823}
{"_id":{"$oid":"56f9e9dc2a00005f00d61884"},"timeline":6,"author_name":"杨典","text":"好看","author_id":3,"like":0,"posted":"2016-03-29T02:34:03.923Z","item_id":6720}
{"_id":{"$oid":"56f9ea182a00006300d61885"},"timeline":8,"author_name":"杨典","text":"有意思","author_id":3,"like":0,"posted":"2016-03-29T02:34:31.899Z","item_id":6720}
{"_id":{"$oid":"56f9eaa42a00006b00d61887"},"timeline":0,"author_name":"杨典","text":"有用","author_id":3,"like":0,"posted":"2016-03-29T02:38:04.439Z","item_id":6863}
{"_id":{"$oid":"56f9ebc92a00007f00d6188a"},"timeline":0,"author_name":"杨典","text":"有道理","author_id":3,"like":0,"posted":"2016-03-29T02:42:39.895Z","item_id":1638}
{"_id":{"$oid":"56f9f75e2a00009e00d6188e"},"timeline":0,"author_name":"杨典","text":"好评","author_id":3,"like":0,"posted":"2016-03-29T03:32:45.935Z","item_id":2419}
{"_id":{"$oid":"56fa2c042a0000c000d61894"},"timeline":30,"author_name":"刘杨","text":"有道理","author_id":5,"like":0,"posted":"2016-03-29T07:17:24.194Z","item_id":2813}
{"_id":{"$oid":"56fb44ea0f00003f0006f338"},"timeline":34,"author_name":"刘杨","text":"OK","author_id":5,"like":0,"posted":"2016-03-30T03:15:52.848Z","item_id":1052}
{"_id":{"$oid":"56fe1bcd4100004300530f4b"},"item_id":1400,"author_id":14,"author_name":"ccvc","posted":"2016-04-01T06:57:16.496Z","text":"并不是","timeline":6,"like":0}
{"_id":{"$oid":"56fe1c904100006100530f54"},"timeline":20,"author_name":"匿名用户","text":"抱抱你","author_id":16,"like":0,"posted":"2016-04-01T07:00:32.669Z","item_id":2572}
{"_id":{"$oid":"56fe1c994100006400530f55"},"timeline":28,"author_name":"匿名用户","text":"抱抱你vv回家","author_id":16,"like":0,"posted":"2016-04-01T07:00:41.232Z","item_id":2572}
{"_id":{"$oid":"56fe1c9c4100006100530f56"},"timeline":31,"author_name":"匿名用户","text":"抱抱你vv回家","author_id":16,"like":0,"posted":"2016-04-01T07:00:44.078Z","item_id":2572}
{"_id":{"$oid":"56fe1c9e4100006800530f57"},"timeline":33,"author_name":"匿名用户","text":"抱抱你vv回家","author_id":16,"like":0,"posted":"2016-04-01T07:00:46.237Z","item_id":2572}
{"_id":{"$oid":"56fe1ca04100006600530f58"},"timeline":35,"author_name":"匿名用户","text":"抱抱你vv回家","author_id":16,"like":0,"posted":"2016-04-01T07:00:48.246Z","item_id":2572}
{"_id":{"$oid":"56fe1ca24100006a00530f59"},"timeline":38,"author_name":"匿名用户","text":"抱抱你vv回家","author_id":16,"like":0,"posted":"2016-04-01T07:00:50.447Z","item_id":2572}
{"_id":{"$oid":"57071c911b0000e001044b11"},"timeline":0,"author_name":"杨典","text":"好","author_id":3,"like":0,"posted":"2016-04-08T02:50:55.915Z","item_id":2495}
{"_id":{"$oid":"570b36861b00001003044b25"},"item_id":6832,"author_id":117,"author_name":"匿名用户","posted":"2016-04-11T05:30:54.458Z","text":"‘TEST’","timeline":22,"like":0}
{"_id":{"$oid":"570b36d11b00001903044b27"},"item_id":8793,"author_id":117,"author_name":"匿名用户","posted":"2016-04-11T05:32:08.758Z","text":"","timeline":2,"like":0}
{"_id":{"$oid":"570b62241b00003903044b2a"},"item_id":703,"author_id":117,"author_name":"匿名用户","posted":"2016-04-11T08:37:00.643Z","text":"'TEST'‘TEST’","timeline":55,"like":0}
{"_id":{"$oid":"570d25331b00007d07044ba3"},"posted":"2016-04-12T16:40:45.977Z","author_id":228,"like":0,"author_name":"匿名用户","text":"好评","timeline":{"$numberLong":"9574275150"},"item_id":5229}
{"_id":{"$oid":"570d25331b00007c07044ba4"},"posted":"2016-04-12T16:40:45.977Z","author_id":228,"like":0,"author_name":"匿名用户","text":"好评","timeline":{"$numberLong":"9574275150"},"item_id":5229}
{"_id":{"$oid":"570d25771b00008707044ba7"},"posted":"2016-04-12T16:42:11.008Z","author_id":229,"like":0,"author_name":"杨典","text":"好评好评","timeline":{"$numberLong":"8764933468"},"item_id":2435}
{"_id":{"$oid":"570d25771b00009207044ba8"},"posted":"2016-04-12T16:42:11.008Z","author_id":229,"like":0,"author_name":"杨典","text":"好评好评","timeline":{"$numberLong":"8764933468"},"item_id":2435}
{"_id":{"$oid":"570d25c01b00009b07044baa"},"posted":"2016-04-12T16:43:38.603Z","author_id":229,"like":0,"author_name":"杨典","text":"好评的","timeline":{"$numberLong":"3911501947"},"item_id":3484}
{"_id":{"$oid":"570d25c21b00009c07044bab"},"posted":"2016-04-12T16:43:38.603Z","author_id":229,"like":0,"author_name":"杨典","text":"好评的","timeline":{"$numberLong":"3911501947"},"item_id":3484}
{"_id":{"$oid":"570d26bf1b0000a007044bad"},"posted":"2016-04-12T16:47:59.535Z","author_id":230,"like":0,"author_name":"匿名用户","text":"棒！","timeline":{"$numberLong":"3361163000"},"item_id":286}
{"_id":{"$oid":"570d26c01b0000a307044bae"},"posted":"2016-04-12T16:47:59.535Z","author_id":230,"like":0,"author_name":"匿名用户","text":"棒！","timeline":{"$numberLong":"3361163000"},"item_id":286}
{"_id":{"$oid":"570d26db1b0000a707044bb0"},"posted":"2016-04-12T16:48:27.674Z","author_id":230,"like":0,"author_name":"杨典","text":"测试","timeline":{"$numberLong":"6465616321"},"item_id":5384}
{"_id":{"$oid":"570d26db1b0000ac07044bb1"},"posted":"2016-04-12T16:48:27.674Z","author_id":230,"like":0,"author_name":"杨典","text":"测试","timeline":{"$numberLong":"6465616321"},"item_id":5384}
{"_id":{"$oid":"570d27bf1b0000ba07044bb4"},"posted":"2016-04-12T16:51:12.910Z","author_id":231,"like":0,"author_name":"杨典","text":"习惯好评","timeline":{"$numberLong":"21393283939"},"item_id":5334}
{"_id":{"$oid":"570d27bf1b0000b207044bb5"},"posted":"2016-04-12T16:51:12.910Z","author_id":231,"like":0,"author_name":"杨典","text":"习惯好评","timeline":{"$numberLong":"21393283939"},"item_id":5334}
{"_id":{"$oid":"570d28741b0000cc07044bb9"},"posted":"2016-04-12T16:54:50.855Z","author_id":232,"like":0,"author_name":"匿名用户","text":"好评","timeline":{"$numberLong":"14591903941"},"item_id":7140}
{"_id":{"$oid":"570d28741b0000cb07044bba"},"posted":"2016-04-12T16:54:50.855Z","author_id":232,"like":0,"author_name":"匿名用户","text":"好评","timeline":{"$numberLong":"14591903941"},"item_id":7140}
{"_id":{"$oid":"570d2b721b0000f607044bc0"},"posted":"2016-04-12T17:07:43.179Z","author_id":236,"like":0,"author_name":"杨典","text":"测试8","timeline":{"$numberLong":"3176321354"},"item_id":5080}
{"_id":{"$oid":"570d2b721b0000ff07044bc1"},"posted":"2016-04-12T17:07:43.179Z","author_id":236,"like":0,"author_name":"杨典","text":"测试8","timeline":{"$numberLong":"3176321354"},"item_id":5080}
{"_id":{"$oid":"570da8bb1b00001808044bc4"},"posted":"2016-04-13T02:02:35.804Z","author_id":238,"like":0,"author_name":"匿名用户","text":" 好","timeline":0,"item_id":8788}
{"_id":{"$oid":"570da8bc1b00001808044bc5"},"posted":"2016-04-13T02:02:35.804Z","author_id":238,"like":0,"author_name":"匿名用户","text":" 好","timeline":0,"item_id":8788}
{"_id":{"$oid":"570dda0a1b0000d808044bdb"},"item_id":1,"author_id":3,"author_name":"测试员","posted":"2016-03-12T7:20:01.000Z","text":"测试内容","timeline":1234560,"like":0}
{"_id":{"$oid":"570e0ade1b0000e509044bf1"},"posted":"2016-04-13T09:01:17.606Z","author_id":0,"like":0,"author_name":"匿名用户","text":"","timeline":0,"item_id":7230}
{"_id":{"$oid":"570e0ade1b0000d609044bf2"},"posted":"2016-04-13T09:01:17.606Z","author_id":0,"like":0,"author_name":"匿名用户","text":"","timeline":0,"item_id":7230}
{"_id":{"$oid":"570e0ade1b0000df09044bf4"},"posted":"2016-04-13T09:01:18.296Z","author_id":276,"like":0,"author_name":"匿名用户","text":"","timeline":0,"item_id":7230}
{"_id":{"$oid":"570e0ade1b0000df09044bf5"},"posted":"2016-04-13T09:01:18.296Z","author_id":276,"like":0,"author_name":"匿名用户","text":"","timeline":0,"item_id":7230}
{"_id":{"$oid":"570e0aef1b0000e309044bf7"},"posted":"2016-04-13T09:01:35.269Z","author_id":277,"like":0,"author_name":"匿名用户","text":"我","timeline":0,"item_id":817}
{"_id":{"$oid":"570e0aef1b0000e009044bf8"},"posted":"2016-04-13T09:01:35.269Z","author_id":277,"like":0,"author_name":"匿名用户","text":"我","timeline":0,"item_id":817}
{"_id":{"$oid":"570f5b291b0000590c044c14"},"posted":"2016-04-14T08:56:09.416Z","author_id":363,"like":0,"author_name":"匿名用户","text":"","timeline":0,"item_id":728}
{"_id":{"$oid":"570f5b291b00005a0c044c15"},"posted":"2016-04-14T08:56:09.416Z","author_id":363,"like":0,"author_name":"匿名用户","text":"","timeline":0,"item_id":728}
{"_id":{"$oid":"570f5b2b1b0000580c044c16"},"posted":"2016-04-14T08:56:11.247Z","author_id":363,"like":0,"author_name":"匿名用户","text":"","timeline":0,"item_id":728}
{"_id":{"$oid":"570f5b2b1b00005b0c044c17"},"posted":"2016-04-14T08:56:11.247Z","author_id":363,"like":0,"author_name":"匿名用户","text":"","timeline":0,"item_id":728}
{"_id":{"$oid":"570f5b2b1b00005b0c044c18"},"posted":"2016-04-14T08:56:11.784Z","author_id":363,"like":0,"author_name":"匿名用户","text":"","timeline":0,"item_id":728}
{"_id":{"$oid":"570f5b2b1b0000560c044c19"},"posted":"2016-04-14T08:56:11.784Z","author_id":363,"like":0,"author_name":"匿名用户","text":"","timeline":0,"item_id":728}
{"_id":{"$oid":"570f5b2c1b00005b0c044c1a"},"posted":"2016-04-14T08:56:12.131Z","author_id":363,"like":0,"author_name":"匿名用户","text":"","timeline":0,"item_id":728}
{"_id":{"$oid":"570f5b2c1b00005a0c044c1b"},"posted":"2016-04-14T08:56:12.131Z","author_id":363,"like":0,"author_name":"匿名用户","text":"","timeline":0,"item_id":728}
{"_id":{"$oid":"570f5b5f1b00005d0c044c1e"},"posted":"2016-04-14T08:57:03.368Z","author_id":364,"like":0,"author_name":"匿名用户","text":"","timeline":0,"item_id":1593}
{"_id":{"$oid":"570f5b5f1b0000600c044c1f"},"posted":"2016-04-14T08:57:03.368Z","author_id":364,"like":0,"author_name":"匿名用户","text":"","timeline":0,"item_id":1593}
{"_id":{"$oid":"570f5b601b0000600c044c20"},"posted":"2016-04-14T08:57:03.885Z","author_id":364,"like":0,"author_name":"匿名用户","text":"","timeline":0,"item_id":1593}
{"_id":{"$oid":"570f5b601b00005d0c044c21"},"posted":"2016-04-14T08:57:03.885Z","author_id":364,"like":0,"author_name":"匿名用户","text":"","timeline":0,"item_id":1593}
{"_id":{"$oid":"570f5b601b0000600c044c22"},"posted":"2016-04-14T08:57:04.291Z","author_id":364,"like":0,"author_name":"匿名用户","text":"","timeline":0,"item_id":1593}
{"_id":{"$oid":"570f5b601b0000650c044c23"},"posted":"2016-04-14T08:57:04.291Z","author_id":364,"like":0,"author_name":"匿名用户","text":"","timeline":0,"item_id":1593}
{"_id":{"$oid":"570f5b601b0000660c044c24"},"posted":"2016-04-14T08:57:04.620Z","author_id":364,"like":0,"author_name":"匿名用户","text":"","timeline":0,"item_id":1593}
{"_id":{"$oid":"570f5b601b0000650c044c25"},"posted":"2016-04-14T08:57:04.620Z","author_id":364,"like":0,"author_name":"匿名用户","text":"","timeline":0,"item_id":1593}
{"_id":{"$oid":"570f5b601b0000600c044c26"},"posted":"2016-04-14T08:57:04.699Z","author_id":364,"like":0,"author_name":"匿名用户","text":"","timeline":0,"item_id":1593}
{"_id":{"$oid":"570f5b601b00005d0c044c27"},"posted":"2016-04-14T08:57:04.699Z","author_id":364,"like":0,"author_name":"匿名用户","text":"","timeline":0,"item_id":1593}
{"_id":{"$oid":"5718a34f2600004e007b00bc"},"item_id":4508,"author_id":458,"author_name":"匿名用户","posted":"2016-04-21T09:54:13.947Z","text":"","timeline":49,"like":0}
